.bumpversion.cfg
LICENSE.md
MANIFEST.in
Makefile
README.md
pyproject.toml
setup.py
FantasyBaseballTrends/FantasyBaseballTrends.py
FantasyBaseballTrends/__init__.py
FantasyBaseballTrends/__main__.py
FantasyBaseballTrends/_version.py
FantasyBaseballTrends.egg-info/PKG-INFO
FantasyBaseballTrends.egg-info/SOURCES.txt
FantasyBaseballTrends.egg-info/dependency_links.txt
FantasyBaseballTrends.egg-info/requires.txt
FantasyBaseballTrends.egg-info/top_level.txt
FantasyBaseballTrends/tests/AaronJudgeCareer.csv
FantasyBaseballTrends/tests/AaronJudgePostseason.csv
FantasyBaseballTrends/tests/AaronJudgeSeason.csv
FantasyBaseballTrends/tests/JudgeCarrerSplits.csv
FantasyBaseballTrends/tests/JudgeLast10.csv
FantasyBaseballTrends/tests/JudgeLast10Avg.csv
FantasyBaseballTrends/tests/JudgeLast5.csv
FantasyBaseballTrends/tests/JudgeLastGame.csv
FantasyBaseballTrends/tests/JudgeLhpCurrent.csv
FantasyBaseballTrends/tests/JudgeRhpCurrent.csv
FantasyBaseballTrends/tests/test.py