Metadata-Version: 2.1
Name: FantasyBaseballTrends
Version: 0.1.2
Summary: Library that helps you search for baseball players stats and trends in order to help with fantasy lineup construction
Author-email: Carlos Gonzalez-Romero <cmg2249@columbia.edu>
License: UNKNOWN
Project-URL: repository, https://github.com/Cargo1284/FantasyBaseballTrends
Platform: UNKNOWN
Classifier: Development Status :: 2 - Pre-Alpha
Classifier: Programming Language :: Python :: Implementation :: CPython
Classifier: Programming Language :: Python :: Implementation :: PyPy
Classifier: Programming Language :: Python :: 3
Classifier: Programming Language :: Python :: 3.7
Classifier: Programming Language :: Python :: 3.8
Classifier: Programming Language :: Python :: 3.9
Classifier: Programming Language :: Python :: 3.10
Classifier: Programming Language :: Python :: 3.11
Requires-Python: >=3.7
Provides-Extra: develop
License-File: LICENSE.md
